README.md
setup.py
npp_materialslab_tools/__init__.py
npp_materialslab_tools.egg-info/PKG-INFO
npp_materialslab_tools.egg-info/SOURCES.txt
npp_materialslab_tools.egg-info/dependency_links.txt
npp_materialslab_tools.egg-info/requires.txt
npp_materialslab_tools.egg-info/top_level.txt
npp_materialslab_tools/dic/__init__.py
npp_materialslab_tools/dic/_old_pydic.py
npp_materialslab_tools/dic/_pydic_support.py
npp_materialslab_tools/dic/dic2d_contour_plot.py
npp_materialslab_tools/dic/dic_grid_plots.py
npp_materialslab_tools/dic/misc.py
npp_materialslab_tools/dic/offset_selector.py
npp_materialslab_tools/dic/pydicGrid.py
npp_materialslab_tools/dic/pydic_displ_processor.py
npp_materialslab_tools/dic/pydic_merge_dic_ut.py
npp_materialslab_tools/dic/pydic_rolling_processor.py
npp_materialslab_tools/dic/pydic_strain_processor.py
npp_materialslab_tools/dmm/__init__.py
npp_materialslab_tools/dmm/tektronix_DMM4020/__init__.py
npp_materialslab_tools/dmm/tektronix_DMM4020/_basic_recording.py
npp_materialslab_tools/dmm/tektronix_DMM4020/_misc.py
npp_materialslab_tools/dmm/tektronix_DMM4020/monitorMeasurementClass.py
npp_materialslab_tools/dmm/tektronix_DMM4020/monitorMeasurementClassDummy.py
npp_materialslab_tools/dmm/tektronix_DMM4020/plot_util.py
npp_materialslab_tools/dmm/tektronix_DMM4020/tekDMM4020.py
npp_materialslab_tools/plottools/__init__.py
npp_materialslab_tools/plottools/cursor_crosshairs.py
npp_materialslab_tools/plottools/point_selector.py
npp_materialslab_tools/plottools/point_selector2.py
npp_materialslab_tools/testing_machine/__init__.py
npp_materialslab_tools/testing_machine/app_ElasticModGUI_v1.py
npp_materialslab_tools/testing_machine/app_ElasticModGUI_v2.py
npp_materialslab_tools/testing_machine/specimen_classes.py
npp_materialslab_tools/testing_machine/tensile_data.py
npp_materialslab_tools/testing_machine/test_appElasticityModulus.py
npp_materialslab_tools/testing_machine/imada/__init__.py
npp_materialslab_tools/testing_machine/imada/imada_tools.py
npp_materialslab_tools/tktools/__init__.py
npp_materialslab_tools/tktools/tk_collapsible_pane.py
npp_materialslab_tools/tktools/tl_ImageProjection.py
npp_materialslab_tools/tktools/tl_matplotlib_graph.py
