Metadata-Version: 2.1
Name: npp-materialslab-tools
Version: 0.0.9
Summary: A package for the material lab tools
Home-page: 
Author: N. Papadakis
Author-email: npapnet@gmail.com
Project-URL: Documentation, https://npapnet.github.io/hmu.materialslab.tools/
Project-URL: Source, https://github.com/npapnet/hmu.materialslab.tools
Classifier: Programming Language :: Python :: 3
Classifier: License :: OSI Approved :: MIT License
Classifier: Operating System :: OS Independent
Requires-Python: >=3.8
